petanalysis/Dog Data all.csv
petanalysis/OrganizationData.csv
petanalysis/US_postcode.csv
petanalysis/__init__.py
petanalysis/assoc_rules.py
petanalysis/location.py
petanalysis/petplot.py
petanalysis/usrerror.py
petanalysis-0.1.3.dist-info/LICENSE.txt
petanalysis-0.1.3.dist-info/METADATA
petanalysis-0.1.3.dist-info/WHEEL
petanalysis-0.1.3.dist-info/top_level.txt
petanalysis-0.1.3.dist-info/RECORD
